GraphClusterer/__init__.py
GraphClusterer/calc_energy.py
GraphClusterer/embed_abstract.py
GraphClusterer/evaluate.py
GraphClusterer/functions.py
GraphClusterer/main.py
GraphClusterer/one_to_rule_them_all.py
GraphClusterer/plot.py
GraphClusterer/starry_graph.py
GraphClusterer/summarize.py
graphclusterer-0.5.0.dist-info/licenses/LICENSE.txt
graphclusterer-0.5.0.dist-info/METADATA
graphclusterer-0.5.0.dist-info/WHEEL
graphclusterer-0.5.0.dist-info/top_level.txt
graphclusterer-0.5.0.dist-info/RECORD
