Metadata-Version: 2.4
Name: GraphClusterer
Version: 0.5.0
Summary: A python package for clustering and summarizing graphs of texts.
Home-page: https://github.com/yoelAshkenazi/GraphClusterer
Author: Yoel Ashkenazi, Regev Yehezkel Imra
Author-email: yoelashkenazi12@gmail.com, regevel2006@gmail.com
Classifier: Programming Language :: Python :: 3
Classifier: License :: OSI Approved :: MIT License
Classifier: Operating System :: OS Independent
Requires-Python: >=3.8
License-File: LICENSE.txt
Requires-Dist: replicate
Requires-Dist: cohere
Requires-Dist: networkx
Requires-Dist: numpy
Requires-Dist: pandas
Requires-Dist: scipy
Requires-Dist: spacy
Requires-Dist: plotly
Requires-Dist: matplotlib
Requires-Dist: chardet
Requires-Dist: requests
Requires-Dist: sentence-transformers
Requires-Dist: dcor
Requires-Dist: scikit-learn
Requires-Dist: leidenalg
Requires-Dist: igraph
Dynamic: license-file
